project_creator/__init__.py
project_creator/create_project.py
aloha_flask_creator-0.1.2.dist-info/LICENSE
aloha_flask_creator-0.1.2.dist-info/METADATA
aloha_flask_creator-0.1.2.dist-info/WHEEL
aloha_flask_creator-0.1.2.dist-info/entry_points.txt
aloha_flask_creator-0.1.2.dist-info/top_level.txt
aloha_flask_creator-0.1.2.dist-info/RECORD
